shapeandshare/command/runner/__init__.py
shapeandshare/command/runner/command_line.py
shapeandshare/command/runner/manager.py
shapeandshare/command/runner/backends/__init__.py
shapeandshare/command/runner/backends/abstract_backend.py
shapeandshare/command/runner/backends/backend_config.py
shapeandshare/command/runner/backends/backend_factory.py
shapeandshare/command/runner/backends/backend_package.py
shapeandshare/command/runner/common/utils.py
shapeandshare/command/runner/contacts/__init__.py
shapeandshare/command/runner/contacts/backend_type.py
shapeandshare/command/runner/contacts/command_type.py
shapeandshare/command/runner/contacts/dtos/__init__.py
shapeandshare/command/runner/contacts/dtos/backend_model.py
shapeandshare/command/runner/contacts/dtos/base_model.py
shapeandshare/command/runner/contacts/dtos/manager/__init__.py
shapeandshare/command/runner/contacts/dtos/manager/command_parameters.py
shapeandshare/command/runner/contacts/dtos/manager/config_parameters.py
shapeandshare/command/runner/contacts/dtos/manager/manager_config.py
shapeandshare/command/runner/contacts/errors/__init__.py
shapeandshare/command/runner/contacts/errors/parse_error.py
shapeandshare/command/runner/contacts/errors/subprocess_failure_error.py
shapeandshare/command/runner/contacts/errors/unknown_argument_error.py
shapeandshare/command/runner/contacts/errors/unknown_command_error.py
shapeandshare/command/runner/contacts/errors/unknown_error.py
sacr-1.1.0.dist-info/LICENSE
sacr-1.1.0.dist-info/METADATA
sacr-1.1.0.dist-info/WHEEL
sacr-1.1.0.dist-info/entry_points.txt
sacr-1.1.0.dist-info/top_level.txt
sacr-1.1.0.dist-info/RECORD
