Metadata-Version: 2.1
Name: sacr
Version: 1.1.0
Summary: Aliased Command Runner
Author: Joshua C. Burt
Author-email: joshburt@shapeandshare.com
License: MIT
Requires-Python: >=3.9
License-File: LICENSE
Requires-Dist: pydantic (>=1.9.0)
